pip_login.py
pip_login-0.0.6.dist-info/LICENSE
pip_login-0.0.6.dist-info/METADATA
pip_login-0.0.6.dist-info/WHEEL
pip_login-0.0.6.dist-info/entry_points.txt
pip_login-0.0.6.dist-info/top_level.txt
pip_login-0.0.6.dist-info/RECORD
